Metadata-Version: 2.1
Name: tf2-initializer
Version: 0.5
Summary: A tf2 project initializer
Home-page: https://github.com/zankner/tf2-initializer
Author: Zack Ankner
Author-email: zackankner@gmail.com
License: UNKNOWN
Platform: UNKNOWN
Classifier: Programming Language :: Python :: 3
Classifier: Operating System :: Unix
